labcrawler/__init__.py
labcrawler/__main__.py
labcrawler/command/__init__.py
labcrawler/command/list_command.py
labcrawler/command/move_command.py
labcrawler/gitlab/__init__.py
labcrawler/gitlab/query/__init__.py
labcrawler/gitlab/query/packages_query.py
labcrawler/gitlab/query/projects_query.py
labcrawler/gitlab/query/subgroups_query.py
labcrawler/gitlab/query/users_query.py
labcrawler-2.2.1.dist-info/LICENSE
labcrawler-2.2.1.dist-info/METADATA
labcrawler-2.2.1.dist-info/WHEEL
labcrawler-2.2.1.dist-info/entry_points.txt
labcrawler-2.2.1.dist-info/RECORD
