Metadata-Version: 2.1
Name: labcrawler
Version: 2.2.1
Summary: Load, analyze, move, and manipulate GitLab data
License: MIT
Author: Francis Potter
Author-email: labcrawler@wizlib.ca
Requires-Python: >=3.11,<3.12
Classifier: License :: OSI Approved :: MIT License
Classifier: Programming Language :: Python :: 3
Classifier: Programming Language :: Python :: 3.11
Requires-Dist: requests (>=2.31.0,<3.0.0)
Requires-Dist: wizlib (>=3.1.3,<4.0.0)
